gradio_dialogue/__init__.py
gradio_dialogue/dialogue.py
gradio_dialogue/dialogue.pyi
gradio_dialogue/templates/component/Index-CUNRk6k7.js
gradio_dialogue/templates/component/_basePickBy-Bhf__bZN.js
gradio_dialogue/templates/component/_baseUniq-DF7h5zIi.js
gradio_dialogue/templates/component/arc-DoDWtOBx.js
gradio_dialogue/templates/component/architectureDiagram-IEHRJDOE--yml2WQN.js
gradio_dialogue/templates/component/blockDiagram-JOT3LUYC-B5KY8dxW.js
gradio_dialogue/templates/component/c4Diagram-VJAJSXHY-ByBUMRRA.js
gradio_dialogue/templates/component/channel-CyiDjNsz.js
gradio_dialogue/templates/component/chunk-4BMEZGHF-BVudHlEM.js
gradio_dialogue/templates/component/chunk-A2AXSNBT-B_UY0N-S.js
gradio_dialogue/templates/component/chunk-AEK57VVT-C_iYECPD.js
gradio_dialogue/templates/component/chunk-D6G4REZN-Cxd1W4NQ.js
gradio_dialogue/templates/component/chunk-RZ5BOZE2-D3xtNKIx.js
gradio_dialogue/templates/component/chunk-XZIHB7SX-B_RPSwQ_.js
gradio_dialogue/templates/component/classDiagram-GIVACNV2-B8e4hXFh.js
gradio_dialogue/templates/component/classDiagram-v2-COTLJTTW-B8e4hXFh.js
gradio_dialogue/templates/component/clone-pAqqpBDa.js
gradio_dialogue/templates/component/cytoscape.esm-Cl3mOukQ.js
gradio_dialogue/templates/component/dagre-OKDRZEBW-W1bmsPPY.js
gradio_dialogue/templates/component/diagram-SSKATNLV-BCRztAmo.js
gradio_dialogue/templates/component/diagram-VNBRO52H-CM_PzwQn.js
gradio_dialogue/templates/component/erDiagram-Q7BY3M3F-B0Z6SDXj.js
gradio_dialogue/templates/component/flowDiagram-4HSFHLVR-CR5wZ8U-.js
gradio_dialogue/templates/component/ganttDiagram-APWFNJXF-BD_XsgA0.js
gradio_dialogue/templates/component/gitGraphDiagram-7IBYFJ6S-E2TClekj.js
gradio_dialogue/templates/component/graph-CMZAUKwA.js
gradio_dialogue/templates/component/index.js
gradio_dialogue/templates/component/infoDiagram-PH2N3AL5-Msp1D_cL.js
gradio_dialogue/templates/component/init-DjUOC4st.js
gradio_dialogue/templates/component/journeyDiagram-U35MCT3I-KxheU6Sg.js
gradio_dialogue-0.0.5.dist-info/METADATA
gradio_dialogue-0.0.5.dist-info/WHEEL
gradio_dialogue-0.0.5.dist-info/RECORD
